xscope_fileio/host/CMakeLists.txt
xscope_fileio/host/README.rst
xscope_fileio/host/__init__.py
xscope_fileio/host/build_host.py
xscope_fileio/host/xscope_io_host.c
xscope_fileio/__init__.py
xscope_fileio/api/xscope_io_device.h
xscope_fileio/config.xscope.txt
xscope_fileio/lib_build_info.cmake
xscope_fileio/module_build_info
xscope_fileio/src/xscope_io_device.c
xscope_fileio/xscope_io_common.h
xscope_fileio-1.3.0.dist-info/LICENSE.rst
xscope_fileio-1.3.0.dist-info/METADATA
xscope_fileio-1.3.0.dist-info/WHEEL
xscope_fileio-1.3.0.dist-info/RECORD
