Metadata-Version: 2.1
Name: xscope-fileio
Version: 1.3.0
Summary: Python module for managing files using xscope
Home-page: https://github.com/xmos/xscope_fileio
License: LICENSE.rst
Author: XMOS
Requires-Python: >=3.10,<3.12
Classifier: License :: Other/Proprietary License
Classifier: Programming Language :: Python :: 3
Classifier: Programming Language :: Python :: 3.10
Classifier: Programming Language :: Python :: 3.11
Requires-Dist: numpy (==1.26.4)
